Workbook

Sheet Costos
A1: Tabla D.1 — Costos estimados del proyecto (CLP)
A2: Anexo D del Documento 0. Azul = dato de entrada; negro = fórmula. Proyecto de 12 meses, 6 roles full-time.
C3: Meses del proyecto | D3: 12
A4: Concepto | B4: Detalle | C4: Valor mensual CLP | D4: Valor anual CLP
A5: Jefe de Proyecto | B5: 1 profesional | C5: 2000000 | D5: =C5*$D$3 -> 24000000
A6: Arquitecto | B6: 1 profesional | C6: 2000000 | D6: =C6*$D$3 -> 24000000
A7: Promotor-DevOps | B7: 1 profesional | C7: 1700000 | D7: =C7*$D$3 -> 20400000
A8: Desarrollador | B8: 1 profesional | C8: 1500000 | D8: =C8*$D$3 -> 18000000
A9: Administrador BD | B9: 1 profesional | C9: 1300000 | D9: =C9*$D$3 -> 15600000
A10: QA / Tester | B10: 1 profesional | C10: 1100000 | D10: =C10*$D$3 -> 13200000
A11: Subtotal RRHH directo | B11: =COUNTA(A5:A10)&" roles full-time" -> 6 roles full-time | C11: =SUM(C5:C10) -> 9600000 | D11: =SUM(D5:D10) -> 115200000
A12: Costos indirectos | B12: ="Administración, oficina, equipamiento ≈"&TEXT(D12/D11,"0%") -> Administración, oficina, equipamiento ≈34% | D12: 39400000
A13: Total RRHH con indirectos | B13: Costo total de equipo profesional | D13: =D11+D12 -> 154600000
A14: Licencias y servicios | B14: SSL, dominio, cloud, DevOps | D14: 470000
A15: Total inversión proyecto | B15: Costo total a 12 meses | D15: =D13+D14 -> 155070000
A17: Fuente: Elaboración propia del equipo a partir de plantilla del curso, 2026.

Sheet Beneficios
A1: Tabla D.2 — Beneficios mensuales y anuales esperados (CLP)
A4: Concepto | B4: Justificación | C4: Valor CLP
A5: Beneficio mensual | B5: Ahorro mensual estimado del sistema en operación | C5: 18000000
A6: Beneficio anual | B6: Beneficio mensual × 12 meses | C6: =C5*Costos!D3 -> 216000000

Sheet ROI
A1: Tabla D.3 — Resumen ejecutivo del análisis ROI
A4: Concepto | B4: Monto CLP
A5: Costo RRHH total con indirectos | B5: =Costos!D13 -> 154600000
A6: Costo licencias y servicios | B6: =Costos!D14 -> 470000
A7: Costo total proyecto | B7: =B5+B6 -> 155070000
A8: Beneficio mensual | B8: =Beneficios!C5 -> 18000000
A9: Beneficio anual | B9: =Beneficios!C6 -> 216000000
A10: Ganancia neta anual | B10: =B9-B7 -> 60930000
A11: ROI 1er año | B11: =B10/B7 -> 0.39291933

Sheet Flujo de caja
A1: Tabla D.4 — Flujo de caja descontado a 12 meses (CLP)
A2: Inversión del período 0 = RRHH directo de un mes + licencias. Flujo neto mensual = beneficio mensual − RRHH directo mensual.
A3: Tasa de descuento mensual | B3: 0.145
A5: Período | B5: Inversión CLP | C5: Flujo neto CLP | D5: Flujo descontado CLP | E5: Flujo de caja total CLP
A6: Período 0 | B6: =-(Costos!C11+Costos!D14) -> -10070000 | D6: =B6 -> -10070000 | E6: =B6 -> -10070000
A7: Mes 1 | C7: =Beneficios!$C$5-Costos!$C$11 -> 8400000 | D7: =C7/(1+$B$3)^1 -> 7336244.5 | E7: =C7 -> 8400000
A8: Mes 2 | C8: =Beneficios!$C$5-Costos!$C$11 -> 8400000 | D8: =C8/(1+$B$3)^2 -> 6407200.5 | E8: =C8 -> 8400000
A9: Mes 3 | C9: =Beneficios!$C$5-Costos!$C$11 -> 8400000 | D9: =C9/(1+$B$3)^3 -> 5595808.3 | E9: =C9 -> 8400000
A10: Mes 4 | C10: =Beneficios!$C$5-Costos!$C$11 -> 8400000 | D10: =C10/(1+$B$3)^4 -> 4887168.8 | E10: =C10 -> 8400000
A11: Mes 5 | C11: =Beneficios!$C$5-Costos!$C$11 -> 8400000 | D11: =C11/(1+$B$3)^5 -> 4268269.7 | E11: =C11 -> 8400000
A12: Mes 6 | C12: =Beneficios!$C$5-Costos!$C$11 -> 8400000 | D12: =C12/(1+$B$3)^6 -> 3727746.5 | E12: =C12 -> 8400000
A13: Mes 7 | C13: =Beneficios!$C$5-Costos!$C$11 -> 8400000 | D13: =C13/(1+$B$3)^7 -> 3255673.8 | E13: =C13 -> 8400000
A14: Mes 8 | C14: =Beneficios!$C$5-Costos!$C$11 -> 8400000 | D14: =C14/(1+$B$3)^8 -> 2843383.2 | E14: =C14 -> 8400000
A15: Mes 9 | C15: =Beneficios!$C$5-Costos!$C$11 -> 8400000 | D15: =C15/(1+$B$3)^9 -> 2483304.1 | E15: =C15 -> 8400000
A16: Mes 10 | C16: =Beneficios!$C$5-Costos!$C$11 -> 8400000 | D16: =C16/(1+$B$3)^10 -> 2168824.5 | E16: =C16 -> 8400000
A17: Mes 11 | C17: =Beneficios!$C$5-Costos!$C$11 -> 8400000 | D17: =C17/(1+$B$3)^11 -> 1894169.9 | E17: =C17 -> 8400000
A18: Mes 12 | C18: =Beneficios!$C$5-Costos!$C$11 -> 8400000 | D18: =C18/(1+$B$3)^12 -> 1654296.9 | E18: =C18 -> 8400000
A19: Suma flujos descontados (meses 1-12) | D19: =SUM(D7:D18) -> 46522091
A20: VAN 12 meses (incluye inversión) | D20: =SUM(D6:D18) -> 36452091
A21: TIR mensual | D21: =IRR(E6:E18) -> 0.83358325
